_infomap.cp38-win_amd64.pyd
infomap.py
package_meta.py
infomap-2.8.0.dist-info/LICENSE
infomap-2.8.0.dist-info/METADATA
infomap-2.8.0.dist-info/WHEEL
infomap-2.8.0.dist-info/entry_points.txt
infomap-2.8.0.dist-info/top_level.txt
infomap-2.8.0.dist-info/RECORD
