Metadata-Version: 2.1
Name: infomap
Version: 2.8.0
Summary: Infomap network clustering algorithm
Home-page: https://mapequation.github.io/infomap/
Author: mapequation
Author-email: mapequation@gmail.com
License: GPL-3.0-or-later
Project-URL: Bug Reports, https://github.com/mapequation/infomap/issues
Project-URL: Source, https://github.com/mapequation/infomap.git
